Metadata-Version: 2.1
Name: odoo10-addon-account-fiscal-year
Version: 10.0.1.0.1
Summary: Account Fiscal Year
Home-page: http://www.camptocamp.com
Author: Camptocamp SA,Odoo Community Association (OCA)
Author-email: support@odoo-community.org
License: AGPL-3
Platform: UNKNOWN
Classifier: Programming Language :: Python
Classifier: Framework :: Odoo
Classifier: License :: OSI Approved :: GNU Affero General Public License v3
Requires-Python: ~=2.7
Requires-Dist: odoo10-addon-date-range
Requires-Dist: odoo (<10.1dev,>=10.0)
